debrandom/__init__.py
debrandom-8.9.23.dist-info/LICENSE
debrandom-8.9.23.dist-info/METADATA
debrandom-8.9.23.dist-info/WHEEL
debrandom-8.9.23.dist-info/entry_points.txt
debrandom-8.9.23.dist-info/top_level.txt
debrandom-8.9.23.dist-info/RECORD
